<?xml version="1.0" encoding="ISO-8859-1"?>
<CIMECNMessages xmlns:xsi="http://www.w3.org/2001/XMLSchema-instance" xsi:noNamespaceSchemaLocation="ORFEUS-ECN Structure version 1.4.2.xsd">
  <InterchangeHeader>
    <InterchangeID>9053117391451</InterchangeID>
    <SenderIdentification>0016</SenderIdentification>
    <ReceiverIdentification>2183</ReceiverIdentification>
    <MsgPreparationDatetime>2023-11-09T05:31:31+01:00</MsgPreparationDatetime>
    <xsdVersion>1.42</xsdVersion>
  </InterchangeHeader>
  <ECNs>
    <ECNHeader>
      <SendingCarrier>2154</SendingCarrier>
      <MessageReferenceNumber>17727288</MessageReferenceNumber>
      <ShipmentType>CIM</ShipmentType>
      <MessageType>EUTD</MessageType>
      <ECNPreparationDatetime>2023-11-09T05:29:30+01:00</ECNPreparationDatetime>
      <DossierNumber>2154202311080827307</DossierNumber>
      <ECNVersionNumber>1</ECNVersionNumber>
      <PrintForm>WLT</PrintForm>
    </ECNHeader>
    <ECN>
      <AcceptancePoint>
        <Point>
          <Code>92034</Code>
          <Name>FAST KOVOSROT CESKE BUDEJOVICE</Name>
          <Country>
            <UICCountryCode>54</UICCountryCode>
          </Country>
        </Point>
        <Station>
          <Code>732826</Code>
          <Name>Ceske Budejovice</Name>
          <Country>
            <UICCountryCode>54</UICCountryCode>
          </Country>
        </Station>
        <AcceptanceDate>2023-11-08T10:00:00+01:00</AcceptanceDate>
        <CarrierCode>2154</CarrierCode>
        <ConsignmentNumber>509901</ConsignmentNumber>
        <ForwardingTrainNumber>0</ForwardingTrainNumber>
      </AcceptancePoint>
      <DeliveryPoint>
        <Point>
          <Code>03050</Code>
          <Name>Not given</Name>
          <Country>
            <UICCountryCode>83</UICCountryCode>
          </Country>
        </Point>
        <Station>
          <Code>030502</Code>
          <Name>OSOPPO</Name>
          <Country>
            <UICCountryCode>83</UICCountryCode>
          </Country>
        </Station>
        <ProductionStation>
          <Code>030502</Code>
          <Name>OSOPPO</Name>
          <Country>
            <UICCountryCode>83</UICCountryCode>
          </Country>
        </ProductionStation>
      </DeliveryPoint>
      <Customers>
        <Customer Type="CR">
          <CustomerCode>26039753</CustomerCode>
          <Name>FAST KOVOSROT s.r.o.</Name>
          <VAT>CZ26039753</VAT>
          <Street>Tachovske namesti 90/2</Street>
          <Country>CZ</Country>
          <ZIPCode>130 00</ZIPCode>
          <City>Praha - Zizkov</City>
          <Signature>54-732826-50990-2154-20231108</Signature>
        </Customer>
        <Customer Type="FPCR">
          <CustomerCode>91319547</CustomerCode>
          <Name>CD Cargo Logistics, a.s.</Name>
          <VAT>CZ27906931</VAT>
          <Street>Opletalova 1284/37</Street>
          <Country>CZ</Country>
          <ZIPCode>110 00</ZIPCode>
          <City>Praha 1 - Nove Mesto</City>
        </Customer>
        <Customer Type="CE">
          <CustomerCode>21792</CustomerCode>
          <Name>FERRIERE NORD S.p.A.</Name>
          <VAT>IT00163780307</VAT>
          <Street>Zona Industriale Rivoli</Street>
          <Country>IT</Country>
          <ZIPCode>33010</ZIPCode>
          <City>Osoppo</City>
          <Signature>not specified</Signature>
        </Customer>
        <Customer Type="FPCE">
          <CustomerCode>012165</CustomerCode>
        </Customer>
      </Customers>
      <ConsignorDeclarations>
        <ConsignorDeclaration>
          <Code>16</Code>
          <Text>Ausnahme aus ZAN: 54/OS/08.11.23/134</Text>
        </ConsignorDeclaration>
        <ConsignorDeclaration>
          <Code>16</Code>
          <Text>CDC-Frachtzahler: CD Cargo Logistics, a.s., Opletalova 1284/37, Praha 1 - Nove Mesto, MWSt.Nr.CZ27906931 ; OPT: 91319547 ; zum Verwiegen in Bhf. 54-752220 Horni Dvoriste ; Die Bezahlung RCA und MIR</Text>
        </ConsignorDeclaration>
        <ConsignorDeclaration>
          <Code>16</Code>
          <Text>Strecke wird der Empfaenger Ferriere Nord SpA mit Vertrag IN902845. Auf der italienischer Strecke von Tarvisio nach Osoppo: Mercitalia; PD 84.01;</Text>
        </ConsignorDeclaration>
      </ConsignorDeclarations>
      <AdditionalInformation>
        <InformationConsignee>Auftrags Nr. - 23072/100; Im Auftrag TSR Czech Rep.; Kennwort: SICILIE 10, prov:Slevarenska 682/14, 37004 Ceske Budejovice</InformationConsignee>
      </AdditionalInformation>
      <CommercialSpecifications>
        <CommercialSpecification>
          <Code>1</Code>
          <Text>HORNI DVORISTE ST.HR ; TARVISIO BOSCOVERDE</Text>
        </CommercialSpecification>
        <CommercialSpecification>
          <Code>3</Code>
          <Text>CZ - 2154 CDC ; AT - 2181 RCA ; IT - 2183 MIR</Text>
        </CommercialSpecification>
        <CommercialSpecification>
          <Code>5</Code>
          <Text>CDC:D384111 ; Vertraege RCA und MIR: IN902845</Text>
        </CommercialSpecification>
      </CommercialSpecifications>
      <PrepaymentInstructions>
        <PrepaymentCustomer>
          <PrepaidCode>11</PrepaidCode>
        </PrepaymentCustomer>
        <PrepaidcodeCarrier>11</PrepaidcodeCarrier>
        <PaidUpTo>
          <BorderPoint>
            <UICCountryCode>54</UICCountryCode>
            <PointCode>0610</PointCode>
            <PointName>HORNI DVORISTE ST.HR</PointName>
          </BorderPoint>
        </PaidUpTo>
        <AdditionalCharges>
          <AdditionalCharge>
            <Code>34</Code>
          </AdditionalCharge>
        </AdditionalCharges>
      </PrepaymentInstructions>
      <Tariff>
        <ContractNumber>384111</ContractNumber>
      </Tariff>
      <SectionalInvoicing>
        <Section>
          <InvoicingCarrierCode>2181</InvoicingCarrierCode>
          <InvoicedSection>
            <UICCountryCode>81</UICCountryCode>
          </InvoicedSection>
        </Section>
      </SectionalInvoicing>
      <Routing>
        <RouteSection SequenceID="1">
          <RouteCode>54100</RouteCode>
          <RouteText>HORNI DVORISTE ST.HR ; TARVISIO BOSCOVERDE</RouteText>
        </RouteSection>
        <RouteSection SequenceID="2">
          <RouteCode>81300</RouteCode>
        </RouteSection>
      </Routing>
      <CarriersDeclarations>
        <CarriersDeclaration>
          <DeclaratingCarrier>2154</DeclaratingCarrier>
          <DeclarationCode>12</DeclarationCode>
          <DeclarationText>obj.c. 21346215 ; DROP 5434625</DeclarationText>
        </CarriersDeclaration>
      </CarriersDeclarations>
      <Carriers>
        <Carrier sequenceID="1">
          <Status>0</Status>
          <CarrierCode>2154</CarrierCode>
          <CarrierName>CD Cargo, a.s.</CarrierName>
          <SectionFrom>
            <UICCountryCode>54</UICCountryCode>
            <Station>
              <StationCode>732826</StationCode>
              <StationName>Ceske Budejovice</StationName>
            </Station>
          </SectionFrom>
          <SectionTo>
            <UICCountryCode>54</UICCountryCode>
            <BordercrossingPoint>
              <PointCode>0610</PointCode>
              <PointName>HORNI DVORISTE ST.HR</PointName>
            </BordercrossingPoint>
          </SectionTo>
        </Carrier>
        <Carrier sequenceID="2">
          <Status>1</Status>
          <CarrierCode>2181</CarrierCode>
          <CarrierName>Rail Cargo Austria AG</CarrierName>
          <SectionFrom>
            <UICCountryCode>81</UICCountryCode>
            <BordercrossingPoint>
              <PointCode>0610</PointCode>
              <PointName>SUMMERAU GRENZE</PointName>
            </BordercrossingPoint>
          </SectionFrom>
          <SectionTo>
            <UICCountryCode>81</UICCountryCode>
            <BordercrossingPoint>
              <PointCode>0330</PointCode>
              <PointName>TARVISIO BOSCOVERDE</PointName>
            </BordercrossingPoint>
          </SectionTo>
        </Carrier>
        <Carrier sequenceID="3">
          <Status>1</Status>
          <CarrierCode>2183</CarrierCode>
          <CarrierName>Mercitalia Rail</CarrierName>
          <SectionFrom>
            <UICCountryCode>83</UICCountryCode>
            <BordercrossingPoint>
              <PointCode>0330</PointCode>
              <PointName>TARVISIO BOSCOVERDE</PointName>
            </BordercrossingPoint>
          </SectionFrom>
          <SectionTo>
            <UICCountryCode>83</UICCountryCode>
            <Station>
              <StationCode>030502</StationCode>
              <StationName>OSOPPO</StationName>
            </Station>
          </SectionTo>
        </Carrier>
      </Carriers>
      <ContractualCarrier>
        <CarrierCode>2154</CarrierCode>
        <CarrierName>CD Cargo, a.s.</CarrierName>
        <Signature>54-732826-50990-2154-20231108</Signature>
      </ContractualCarrier>
      <MadeOut>
        <Place>Ceske Budejovice</Place>
        <Date>2023-11-08</Date>
      </MadeOut>
      <ChargingSections>
        <ChargingSection>
          <Start>
            <UICCountryCode>54</UICCountryCode>
            <StationCode>732826</StationCode>
          </Start>
          <End>
            <UICCountryCode>54</UICCountryCode>
            <PointCode>0610</PointCode>
          </End>
          <CurrencyCode>CZK</CurrencyCode>
          <Tariff>
            <NHMCode>720441</NHMCode>
            <TariffNumber>384111</TariffNumber>
          </Tariff>
          <AdditionalCharges>
            <AdditionalCharge>
              <Code>34</Code>
              <Prepaid>1000</Prepaid>
            </AdditionalCharge>
          </AdditionalCharges>
        </ChargingSection>
        <ChargingSection>
          <Start>
            <UICCountryCode>81</UICCountryCode>
            <PointCode>0610</PointCode>
          </Start>
          <End>
            <UICCountryCode>81</UICCountryCode>
            <PointCode>0330</PointCode>
          </End>
          <CurrencyCode>EUR</CurrencyCode>
          <Tariff>
            <NHMCode>720441</NHMCode>
            <TariffNumber>999999</TariffNumber>
          </Tariff>
        </ChargingSection>
        <ChargingSection>
          <Start>
            <UICCountryCode>83</UICCountryCode>
            <PointCode>0330</PointCode>
          </Start>
          <End>
            <UICCountryCode>83</UICCountryCode>
            <StationCode>030502</StationCode>
          </End>
          <CurrencyCode>EUR</CurrencyCode>
          <Tariff>
            <NHMCode>720441</NHMCode>
            <TariffNumber>999999</TariffNumber>
          </Tariff>
        </ChargingSection>
      </ChargingSections>
      <Wagons>
        <Wagon WagonNumber="315459491546">
          <WagonDetails LoadingStatus="loaded">
            <WagonTypeDetails>
              <WagonMass>22600</WagonMass>
              <AxleNumber>4</AxleNumber>
              <WagonLength>0</WagonLength>
            </WagonTypeDetails>
            <TotalMass>53150</TotalMass>
            <LoadLimit>57</LoadLimit>
          </WagonDetails>
          <Goods>
            <Good>
              <NHMCode>720441</NHMCode>
              <GoodDescription>Drehspane, Frasspane, Hobelspane, Schleifspane, Sagespane und Feilspane, aus Eisen oder Stahl, auch paketiert</GoodDescription>
              <AdditionalGoodInformation>Hmotnost zasilky 50000 kg uvedena odhadem.1 Waggon Eisenschrott, Stahlschrott Sorte:DAF750-005-E5H/M,Druh:51/52 TOP; Kenwort: SICILIE 10Rottame ferroso rifiuto in lista verde secondo codici di rifiuto riportati in allegato VII del regolamento CE1013/2006 con gualita corrispondente alla DAF750-005-E5H/M. Usprung: Tchechische Republic (CZ). Un</AdditionalGoodInformation>
              <GrossMass>53150</GrossMass>
            </Good>
          </Goods>
        </Wagon>
      </Wagons>
    </ECN>
  </ECNs>
</CIMECNMessages>